bcp/__init__.py
bcp/__main__.py
bcp_reader-0.1.1.dist-info/LICENCE.txt
bcp_reader-0.1.1.dist-info/METADATA
bcp_reader-0.1.1.dist-info/WHEEL
bcp_reader-0.1.1.dist-info/entry_points.txt
bcp_reader-0.1.1.dist-info/top_level.txt
bcp_reader-0.1.1.dist-info/RECORD
