Metadata-Version: 2.1
Name: bcp-reader
Version: 0.1.1
Summary: Stream and convert BCP format files
Home-page: http://github.com/drkane/bcp-reader
Author: David Kane
Author-email: david@dkane.net
License: MIT
Keywords: bcp convert csv
Platform: UNKNOWN
Classifier: Development Status :: 3 - Alpha
Classifier: License :: OSI Approved :: MIT License
Classifier: Programming Language :: Python :: 3.5
Classifier: Programming Language :: Python :: 3.6
Classifier: Programming Language :: Python :: 3.7
Classifier: Programming Language :: Python :: 3.8
Classifier: Programming Language :: Python :: 3 :: Only
